{"tid":"46810","step_name":"step 11","screen_name":"step 11","step_api_url":"","display_as_modal":0,"dismiss_modal":0,"conditional":false,"step_action":{"api_information":"","message_code":"","additional_parameters":[]},"event_list":[],"step_style":{"background_color":"","background_image":{"path":"","asset_status":""},"resolution_unit":"","step_height":"","step_width":"","font_size":"","font_style":"","font_name":"","font_color":"","bootstrap_class_name":"","custom_class_name":"","header_footer_styling":{"header_view_description":{"desc":""},"footer_view_description":{"desc":""}}},"template":[],"dependency_condition":{"condition":[],"query":""},"meta_title":"","meta_description":"","section":[]}